test_work3/__init__.py
test_work3/utils.py
test_work3/server/__init__.py
test_work3/server/__main__.py
test_work3/server/mcp/__init__.py
test_work3/server/mcp/content.py
test_work3/server/mcp/math.py
test_work3/server/mcp/resource.py
test_work3/server/mcp/weather.py
test_work3/server/models/__init__.py
test_work3/server/models/models.py
test_work3/server/routers/__init__.py
test_work3/server/routers/admin.py
test_work3/server/routers/user.py
test_work3/server/utils/__init__.py
test_work3/server/utils/auth_backends.py
test_work3/server/utils/database.py
test_work3/server/utils/user_manager.py
test_work3-0.1.1.dist-info/METADATA
test_work3-0.1.1.dist-info/WHEEL
test_work3-0.1.1.dist-info/top_level.txt
test_work3-0.1.1.dist-info/RECORD
